s3sqlite_db/__init__.py
s3sqlite_db/database.py
s3sqlite_db/url.py
s3sqlite_db-0.1.2.dist-info/LICENSE
s3sqlite_db-0.1.2.dist-info/WHEEL
s3sqlite_db-0.1.2.dist-info/METADATA
s3sqlite_db-0.1.2.dist-info/RECORD
