Metadata-Version: 2.1
Name: s3sqlite-db
Version: 0.1.2
Summary: 
Home-page: https://github.com/smetam/s3sqlite-db
Author: Smetanin Aleksandr
Author-email: smetamx@gmail.com
Requires-Python: >=3.7,<4.0
Classifier: Programming Language :: Python :: 3
Classifier: Programming Language :: Python :: 3.10
Classifier: Programming Language :: Python :: 3.7
Classifier: Programming Language :: Python :: 3.8
Classifier: Programming Language :: Python :: 3.9
Requires-Dist: boto3 (>=1.24.31,<2.0.0)
Requires-Dist: databases[aiosqlite] (>=0.6.0,<0.7.0)
